pyoptflow/__init__.py
pyoptflow/hornschunck.py
pyoptflow/io.py
pyoptflow/lucaskanade.py
pyoptflow/plots.py
pyoptflow-1.3.0.data/scripts/HornSchunck.py
pyoptflow-1.3.0.data/scripts/LucasKanade.py
pyoptflow-1.3.0.dist-info/DESCRIPTION.rst
pyoptflow-1.3.0.dist-info/METADATA
pyoptflow-1.3.0.dist-info/RECORD
pyoptflow-1.3.0.dist-info/WHEEL
pyoptflow-1.3.0.dist-info/metadata.json
pyoptflow-1.3.0.dist-info/top_level.txt
