Metadata-Version: 2.0
Name: pyoptflow
Version: 1.3.0
Summary: Pure Python optical flow: Horn-Schunck
Home-page: https://github.com/scivision/pyoptflow
Author: Michael Hirsch, Ph.D.
Author-email: UNKNOWN
License: UNKNOWN
Platform: UNKNOWN
Classifier: Development Status :: 4 - Beta
Classifier: Environment :: Console
Classifier: Intended Audience :: Science/Research
Classifier: Operating System :: OS Independent
Classifier: Programming Language :: Python :: 3.6
Classifier: Programming Language :: Python :: 3.7
Classifier: Topic :: Scientific/Engineering
Requires-Python: >=3.6
Requires-Dist: imageio
Requires-Dist: numpy
Requires-Dist: scikit-image
Requires-Dist: scipy
Provides-Extra: plot
Requires-Dist: matplotlib; extra == 'plot'
Provides-Extra: tests
Requires-Dist: coveralls; extra == 'tests'
Requires-Dist: nose; extra == 'tests'
Requires-Dist: pytest; extra == 'tests'
